logit/__init__.py
logit/base_logger.py
logit/db_logger.py
logit/default_logger.py
logit/multi_logger.py
logit/conf/__init__.py
logit/conf/logit_conf.py
logit/conf/logit_db_conf.py
logit/conf/logit_multi_conf.py
gaea_logit-1.2.0.dist-info/METADATA
gaea_logit-1.2.0.dist-info/WHEEL
gaea_logit-1.2.0.dist-info/top_level.txt
gaea_logit-1.2.0.dist-info/RECORD
