Metadata-Version: 2.1
Name: gaea-logit
Version: 1.2.0
Summary: A common logger library.
Home-page: https://console.cloud.baidu-int.com/devops/icode/repos/baidu/themis/logger-python/tree/master
Requires-Python: >=3.9
